MANIFEST.in
setup.py
thinkbayes.py
thinkbayes2.py
thinkdsp.py
thinkplot.py
thinkstats2.py
thinkx.egg-info/PKG-INFO
thinkx.egg-info/SOURCES.txt
thinkx.egg-info/dependency_links.txt
thinkx.egg-info/not-zip-safe
thinkx.egg-info/requires.txt
thinkx.egg-info/top_level.txt