Metadata-Version: 1.0
Name: thinkx
Version: 1.1.3
Summary: Modules supporting books by Allen Downey
Home-page: http://github.com/AllenDowney/ThinkX
Author: Allen Downey
Author-email: downey@allendowney.com
License: MIT
Platform: UNKNOWN
